birdcount/__init__.py
birdcount/audio.py
birdcount/cli.py
birdcount/config.py
birdcount/ml.py
birdcount/pipelines.py
birdcount/reports.py
birdcount-0.1.0.dist-info/licenses/LICENSE
birdcount-0.1.0.dist-info/METADATA
birdcount-0.1.0.dist-info/WHEEL
birdcount-0.1.0.dist-info/entry_points.txt
birdcount-0.1.0.dist-info/top_level.txt
birdcount-0.1.0.dist-info/RECORD
