Metadata-Version: 2.4
Name: birdcount
Version: 0.1.0
Summary: Bird call counting and analysis tool
Author-email: Sean Rowland <seanwrowland@gmail.com>
License: MIT
Project-URL: Homepage, https://github.com/seanwrowland/birdcount
Project-URL: Repository, https://github.com/seanwrowland/birdcount
Project-URL: Documentation, https://github.com/seanwrowland/birdcount#readme
Project-URL: Bug Tracker, https://github.com/seanwrowland/birdcount/issues
Keywords: bird,audio,analysis,clustering,machine-learning,bioacoustics
Classifier: Development Status :: 4 - Beta
Classifier: Intended Audience :: Science/Research
Classifier: License :: OSI Approved :: MIT License
Classifier: Operating System :: OS Independent
Classifier: Programming Language :: Python :: 3
Classifier: Programming Language :: Python :: 3.8
Classifier: Programming Language :: Python :: 3.9
Classifier: Programming Language :: Python :: 3.10
Classifier: Programming Language :: Python :: 3.11
Classifier: Programming Language :: Python :: 3.12
Classifier: Topic :: Scientific/Engineering :: Bio-Informatics
Classifier: Topic :: Multimedia :: Sound/Audio :: Analysis
Requires-Python: >=3.8
License-File: LICENSE
Requires-Dist: numpy<2.0.0,>=1.20.0
Requires-Dist: scipy>=1.7.0
Requires-Dist: librosa>=0.9.0
Requires-Dist: matplotlib>=3.5.0
Requires-Dist: seaborn>=0.11.0
Requires-Dist: hdbscan>=0.8.0
Requires-Dist: umap-learn>=0.5.0
Requires-Dist: scikit-learn>=1.0.0
Requires-Dist: pyyaml>=6.0
Requires-Dist: plotly>=5.0.0
Requires-Dist: pandas<2.0.0,>=1.3.0
Requires-Dist: soundfile>=0.12.0
Requires-Dist: tqdm>=4.60.0
Provides-Extra: dev
Requires-Dist: pytest>=6.0; extra == "dev"
Requires-Dist: black>=22.0; extra == "dev"
Requires-Dist: flake8>=4.0; extra == "dev"
Provides-Extra: ml
Requires-Dist: tensorflow>=2.8.0; extra == "ml"
Requires-Dist: tensorflow-hub>=0.12.0; extra == "ml"
Dynamic: license-file
